jsh_py3/__init__.py
jsh_py3/client.py
jsh_py3/exceptions.py
jsh_py3-0.1.0.dist-info/LICENSE
jsh_py3-0.1.0.dist-info/METADATA
jsh_py3-0.1.0.dist-info/WHEEL
jsh_py3-0.1.0.dist-info/top_level.txt
jsh_py3-0.1.0.dist-info/RECORD
