Metadata-Version: 2.1
Name: jsh-py3
Version: 0.1.0
Summary: Junos-like shell library for Python 3
Home-page: https://github.com/A-c0rN/jsh_py3
Author: A-c0rN
Author-email: acrn@gwes-eas.network
License: ODbL-1.0
Keywords: audio sound eas alerting emergency-alert-system
Classifier: Development Status :: 5 - Production/Stable
Classifier: Intended Audience :: Developers
Classifier: License :: OSI Approved :: Apache Software License
Classifier: Programming Language :: Python
Classifier: Programming Language :: Python :: 3
Classifier: Programming Language :: Python :: 3.2
Classifier: Programming Language :: Python :: 3.3
Classifier: Programming Language :: Python :: 3.6
Classifier: Programming Language :: Python :: 3.8
Classifier: Topic :: Software Development :: Libraries :: Python Modules
License-File: LICENSE
Requires-Dist: six
Requires-Dist: readline
